sphinxcontrib_linkattr-0.2.2-py3.8-nspkg.pth
sphinxcontrib/linkattr.py
sphinxcontrib_linkattr-0.2.2.dist-info/LICENSE
sphinxcontrib_linkattr-0.2.2.dist-info/METADATA
sphinxcontrib_linkattr-0.2.2.dist-info/WHEEL
sphinxcontrib_linkattr-0.2.2.dist-info/namespace_packages.txt
sphinxcontrib_linkattr-0.2.2.dist-info/top_level.txt
sphinxcontrib_linkattr-0.2.2.dist-info/RECORD
