Metadata-Version: 2.1
Name: sphinxcontrib-linkattr
Version: 0.2.2
Summary: Sphinx "linkattr" extension
Home-page: https://github.com/tatsushi-ikeda/sphinxcontrib-linkattr
Author: tatsushi-ikeda
Author-email: ikeda.tatsushi.37u@kyoto-u.jp
Maintainer: tatsushi-ikeda
Maintainer-email: ikeda.tatsushi.37u@kyoto-u.jp
License: MIT
Download-URL: http://pypi.python.org/pypi/sphinxcontrib-linkattr
Platform: any
Classifier: Development Status :: 4 - Beta
Classifier: Environment :: Console
Classifier: Environment :: Web Environment
Classifier: Intended Audience :: Developers
Classifier: License :: OSI Approved :: MIT License
Classifier: Operating System :: OS Independent
Classifier: Programming Language :: Python
Classifier: Topic :: Documentation :: Sphinx
Classifier: Topic :: Utilities
License-File: LICENSE
Requires-Dist: sphinx (>=0.6)
